MANIFEST.in
README.rst
setup.py
bin/protoc-gen-python3
protobuf3/__init__.py
protobuf3/list_wrapper.py
protobuf3/message.py
protobuf3/wire_types.py
protobuf3.egg-info/PKG-INFO
protobuf3.egg-info/SOURCES.txt
protobuf3.egg-info/dependency_links.txt
protobuf3.egg-info/top_level.txt
protobuf3/compiler/__init__.py
protobuf3/compiler/plugin_api.py
protobuf3/fields/__init__.py
protobuf3/fields/base.py
protobuf3/fields/bool.py
protobuf3/fields/bytes.py
protobuf3/fields/double.py
protobuf3/fields/enum.py
protobuf3/fields/fixed32.py
protobuf3/fields/fixed64.py
protobuf3/fields/float.py
protobuf3/fields/int32.py
protobuf3/fields/int64.py
protobuf3/fields/message.py
protobuf3/fields/sfixed32.py
protobuf3/fields/sfixed64.py
protobuf3/fields/sint32.py
protobuf3/fields/sint64.py
protobuf3/fields/string.py
protobuf3/fields/uint32.py
protobuf3/fields/uint64.py