Metadata-Version: 1.1
Name: protobuf3
Version: 0.2.0
Summary: Protocol buffers library for Python 3
Home-page: https://github.com/Pr0Ger/protobuf3
Author: Pr0Ger
Author-email: me@pr0ger.org
License: MIT
Platform: UNKNOWN
Classifier: Development Status :: 4 - Beta
Classifier: License :: OSI Approved :: MIT License
Classifier: Operating System :: OS Independent
Classifier: Programming Language :: Python :: 3.3
Classifier: Programming Language :: Python :: 3.4
